stepseries/__init__.py
stepseries/commands.py
stepseries/exceptions.py
stepseries/responses.py
stepseries/server.py
stepseries/step400.py
stepseries/step800.py
stepseries/stepXXX.py
python_step_series-1.0.0.dist-info/LICENSE.txt
python_step_series-1.0.0.dist-info/METADATA
python_step_series-1.0.0.dist-info/WHEEL
python_step_series-1.0.0.dist-info/top_level.txt
python_step_series-1.0.0.dist-info/RECORD
