Metadata-Version: 2.1
Name: python-step-series
Version: 1.0.0
Summary: A Python library for OSC communication with the Ponoor Step-series devices.
Home-page: https://github.com/ponoor/python-step-series
Author: Julian_Orteil
Author-email: 
License: MIT
Project-URL: Source, https://github.com/ponoor/python-step-series
Project-URL: Changelog, https://github.com/ponoor/python-step-series/blob/main/CHANGELOG.rst
Project-URL: Tracker, https://github.com/ponoor/python-step-series/issues
Keywords: ponoor,step400,step800,motor
Platform: any
Classifier: Development Status :: 2 - Pre-Alpha
Classifier: Programming Language :: Python
Classifier: Programming Language :: Python :: 3
Classifier: Programming Language :: Python :: 3 :: Only
Classifier: Programming Language :: Python :: 3.8
Classifier: Programming Language :: Python :: 3.9
Classifier: Programming Language :: Python :: 3.10
Classifier: Intended Audience :: Developers
Classifier: License :: OSI Approved :: MIT License
Classifier: Operating System :: OS Independent
Requires-Python: >=3.7
License-File: LICENSE.txt
Requires-Dist: python-osc
Requires-Dist: importlib-metadata ; python_version < "3.8"
Provides-Extra: testing
Requires-Dist: setuptools ; extra == 'testing'
Requires-Dist: pytest ; extra == 'testing'
Requires-Dist: pytest-cov ; extra == 'testing'
Requires-Dist: pytest-order ; extra == 'testing'
